gar_vis/__init__.py
gar_vis/gar_vis.py
gar_vis/neighbour_viewer.py
gar_vis/util.py
gar_vis-0.1.2.dist-info/licenses/LICENSE
gar_vis-0.1.2.dist-info/METADATA
gar_vis-0.1.2.dist-info/WHEEL
gar_vis-0.1.2.dist-info/top_level.txt
gar_vis-0.1.2.dist-info/RECORD
