Metadata-Version: 2.4
Name: gar-vis
Version: 0.1.2
Summary: Visualisation tool for Corpus Graphs
Author: Martijn Smits
License: MIT License
Project-URL: Repository, https://github.com/martijnsmits/gar_vis
Keywords: information retrieval,corpus graph,visualisation
Classifier: Programming Language :: Python :: 3
Classifier: License :: OSI Approved :: MIT License
Classifier: Operating System :: OS Independent
Requires-Python: >=3.8
License-File: LICENSE
Requires-Dist: python-terrier<1,>=0.10.0
Requires-Dist: pyterrier-adaptive<1,>=0.1.0
Requires-Dist: pyterrier-pisa<1,>=0.1.0
Requires-Dist: h5py<4,>=3.0.0
Requires-Dist: matplotlib<4,>=3.7.0
Requires-Dist: seaborn<1,>=0.13.2
Requires-Dist: numpy<2,>=1.24.0
Requires-Dist: pandas<3,>=2.0.3
Dynamic: license-file
